icengine/__init__.py
icengine/main.py
icengine-0.0.3.dist-info/METADATA
icengine-0.0.3.dist-info/WHEEL
icengine-0.0.3.dist-info/top_level.txt
icengine-0.0.3.dist-info/RECORD
