Metadata-Version: 2.1
Name: icengine
Version: 0.0.3
Summary: A Visual Game Engine For Python
Author: MetalDEV
Author-email: <theducktalkshow@gmail.com>
Keywords: python,game engine
Classifier: Development Status :: 1 - Planning
Classifier: Intended Audience :: Developers
Classifier: Programming Language :: Python :: 3
Classifier: Operating System :: Microsoft :: Windows
